outcome/read_toml/bin.py
outcome/read_toml/lib.py
outcome_read_toml-2.1.1.dist-info/entry_points.txt
outcome_read_toml-2.1.1.dist-info/WHEEL
outcome_read_toml-2.1.1.dist-info/METADATA
outcome_read_toml-2.1.1.dist-info/RECORD
