Metadata-Version: 2.1
Name: outcome-read-toml
Version: 2.1.1
Summary: A small utility to read keys from TOML files.
Home-page: https://github.com/outcome-co/read-toml-py
Author: Outcome Engineering
Author-email: engineering@outcome.co
Requires-Python: >=3.8.5,<4.0.0
Classifier: Programming Language :: Python :: 3
Classifier: Programming Language :: Python :: 3.9
Requires-Dist: click (>=7.1.2,<8.0.0)
Requires-Dist: toml (>=0.10.1,<0.11.0)
Project-URL: Documentation, https://github.com/outcome-co/read-toml-py#README
Project-URL: Repository, https://github.com/outcome-co/read-toml-py
